{
    "title": "Medios y Recursos para Fundaci\u00f3n FAAN - Rescate y Adopci\u00f3n de Animale",
    "description": "Medios y Recursos - Fundaci\u00f3n FAAN, Familia Amor y Animale-Rescate y adopci\u00f3n de animales",
    "keywords": "Medios y Recursos,FAAN,Ecuador,Rescate y adopci\u00f3n,animale",
    "og_title": "Medios y Recursos para Famalia Amor y Animale-FAAN-Ecuador",
    "og_description": "Medios y Recursos - Fundaci\u00f3n FAAN, Familia Amor y Animale-Rescate y adopci\u00f3n de animales",
    "og_image": "\/assets\/img\/faan-logo.png"
}